tsg/__init__.py
tsg/cli.py
tsg/generate_script.py
testing_step_generator-0.1.2.dist-info/METADATA
testing_step_generator-0.1.2.dist-info/WHEEL
testing_step_generator-0.1.2.dist-info/entry_points.txt
testing_step_generator-0.1.2.dist-info/top_level.txt
testing_step_generator-0.1.2.dist-info/RECORD
