Metadata-Version: 2.1
Name: testing_step_generator
Version: 0.1.2
Summary: A CLI tool for initializing and generating output.
Home-page: https://github.com/kel89/testing-step-generator
Author: Your Name
Author-email: kel89@cornell.edu
Classifier: Programming Language :: Python :: 3
Classifier: Operating System :: OS Independent
Requires-Python: >=3.11
Requires-Dist: openai
